{
  "cell": "grok-3-16k",
  "safe_cell": "grok-3-16k",
  "samples": 125,
  "sample_kind_counts": {
    "GENERIC_ESSAY": 67,
    "EXPRESSIVE_FREEFLOW": 57,
    "GENRE_FICTION": 1
  },
  "confidence_counts": {
    "Medium": 75,
    "Low": 39,
    "UNKNOWN": 1,
    "High": 10
  },
  "condition_counts": {
    "LONG": 25,
    "MID": 25,
    "OPEN": 25,
    "SHORT": 25,
    "VARY": 25
  },
  "source_models": [
    "grok-3"
  ],
  "packet": "analysis/freeflow/personality-aggregates/grok-3-16k/packet.md",
  "aggregate": "analysis/freeflow/personality-aggregates/grok-3-16k/aggregate.md"
}